pySlipQt/__init__.py
pySlipQt/blue_marble.py
pySlipQt/gmt_local.py
pySlipQt/log.py
pySlipQt/mapquest.py
pySlipQt/modest_maps.py
pySlipQt/open_street_map.py
pySlipQt/pySlipQt.py
pySlipQt/pycacheback.py
pySlipQt/stamen_toner.py
pySlipQt/stamen_transport.py
pySlipQt/stamen_watercolor.py
pySlipQt/sys_tile_data.py
pySlipQt/tiles.py
pySlipQt/tiles_net.py
pySlipQt/examples/README.rst
pySlipQt/examples/display_text.py
pySlipQt/examples/image_placement.py
pySlipQt/examples/layer_control.py
pySlipQt/examples/make_gmt_tiles.py
pySlipQt/examples/numofcpus.py
pySlipQt/examples/point_placement.py
pySlipQt/examples/pyslipqt_demo.py
pySlipQt/examples/test_assumptions.py
pySlipQt/examples/test_display_text.py
pySlipQt/examples/test_displayable_levels.py
pySlipQt/examples/test_gmt_local_tiles.py
pySlipQt/examples/test_gotoposition.py
pySlipQt/examples/test_image_placement.py
pySlipQt/examples/test_layer_control.py
pySlipQt/examples/test_maprel_image.py
pySlipQt/examples/test_maprel_polygon.py
pySlipQt/examples/test_maprel_text.py
pySlipQt/examples/test_multi_widget.py
pySlipQt/examples/test_osm_tiles.py
pySlipQt/examples/test_point_placement.py
pySlipQt/examples/test_polygon_placement.py
pySlipQt/examples/test_polyline_placement.py
pySlipQt/examples/test_text_placement.py
pySlipQt/examples/test_viewrel_image.py
pySlipQt/examples/test_viewrel_point.py
pySlipQt/examples/test_viewrel_polygon.py
pySlipQt/examples/test_viewrel_text.py
pySlipQt/examples/text_placement.py
pySlipQt/examples/tkinter_error.py
pySlipQt/examples/utils.py
pySlipQt/examples/graphics/Qt_logo.png
pySlipQt/examples/graphics/arrow_down.png
pySlipQt/examples/graphics/arrow_left.png
pySlipQt/examples/graphics/arrow_leftdown.png
pySlipQt/examples/graphics/arrow_leftup.png
pySlipQt/examples/graphics/arrow_right.png
pySlipQt/examples/graphics/arrow_rightdown.png
pySlipQt/examples/graphics/arrow_rightup.png
pySlipQt/examples/graphics/arrow_up.png
pySlipQt/examples/graphics/compass_rose.png
pySlipQt-0.5.1.dist-info/LICENSE
pySlipQt-0.5.1.dist-info/METADATA
pySlipQt-0.5.1.dist-info/WHEEL
pySlipQt-0.5.1.dist-info/top_level.txt
pySlipQt-0.5.1.dist-info/RECORD
