Metadata-Version: 2.1
Name: pySlipQt
Version: 0.5.1
Summary: A slipmap widget for PyQt5
Home-page: http://github.com/rzzzwilson/pySlipQt
Author: Ross Wilson
Author-email: rzzzwilson@gmail.com
License: MIT
Download-URL: https://github.com/rzzzwilson/pySlipQt/releases/tag/0.5.1
Keywords: python pyqt5 slipmap map
Platform: UNKNOWN
Classifier: Development Status :: 4 - Beta
Classifier: Intended Audience :: Developers
Classifier: License :: OSI Approved :: MIT License
Classifier: Operating System :: OS Independent
Classifier: Programming Language :: Python :: 3 :: Only
Requires-Dist: pyqt5
